pathlist/__init__.py
pathlist/path.py
pathlist-0.0.3.dist-info/LICENSE
pathlist-0.0.3.dist-info/METADATA
pathlist-0.0.3.dist-info/WHEEL
pathlist-0.0.3.dist-info/top_level.txt
pathlist-0.0.3.dist-info/RECORD
