Metadata-Version: 2.1
Name: pathlist
Version: 0.0.3
Summary: A Python library that extends pathlib with enhanced path manipulation and directory listing capabilities.
Home-page: https://github.com/susuky/pathlist
Author: susuky
Author-email: hpisj322@gmail.com
Classifier: Programming Language :: Python :: 3
Classifier: License :: OSI Approved :: MIT License
Classifier: Operating System :: OS Independent
Requires-Python: >=3.6
License-File: LICENSE
